dicodile/__init__.py
dicodile/_dicodile.py
dicodile/config.py
dicodile/version.py
dicodile/data/__init__.py
dicodile/data/_text.py
dicodile/data/gait.py
dicodile/data/images.py
dicodile/data/simulate.py
dicodile/update_d/__init__.py
dicodile/update_d/loss_and_gradient.py
dicodile/update_d/optim.py
dicodile/update_d/update_d.py
dicodile/update_z/__init__.py
dicodile/update_z/coordinate_descent.py
dicodile/update_z/dicod.py
dicodile/update_z/distributed_sparse_encoder.py
dicodile/utils/__init__.py
dicodile/utils/constants.py
dicodile/utils/csc.py
dicodile/utils/debug_flags.py
dicodile/utils/debugs.py
dicodile/utils/dictionary.py
dicodile/utils/mpi.py
dicodile/utils/order_iterator.py
dicodile/utils/plot_config.py
dicodile/utils/profile_this.py
dicodile/utils/segmentation.py
dicodile/utils/shape_helpers.py
dicodile/utils/testing.py
dicodile/utils/utils.py
dicodile/utils/viz.py
dicodile/workers/__init__.py
dicodile/workers/dicod_worker.py
dicodile/workers/dicodile_worker.py
dicodile/workers/main_worker.py
dicodile/workers/mpi_workers.py
dicodile-0.3.dist-info/LICENSE
dicodile-0.3.dist-info/METADATA
dicodile-0.3.dist-info/WHEEL
dicodile-0.3.dist-info/top_level.txt
dicodile-0.3.dist-info/RECORD
