Metadata-Version: 2.1
Name: dicodile
Version: 0.3
Summary: Distributed Convolutional Dictionary Learning
Download-URL: https://github.com/tomMoral/dicodile.git
Maintainer: Thomas Moreau
Maintainer-email: thomas.moreau@inria.fr
License: BSD (3-clause)
Platform: any
Classifier: Intended Audience :: Science/Research
Classifier: Intended Audience :: Developers
Classifier: License :: OSI Approved
Classifier: Programming Language :: Python
Classifier: Topic :: Software Development
Classifier: Topic :: Scientific/Engineering
Classifier: Operating System :: POSIX
Classifier: Operating System :: Unix
License-File: LICENSE
Requires-Dist: numpy
Requires-Dist: numba (>=0.53.1)
Requires-Dist: scipy
Requires-Dist: matplotlib
Requires-Dist: mpi4py
Requires-Dist: threadpoolctl
Requires-Dist: joblib
Requires-Dist: download
Requires-Dist: pandas
Provides-Extra: dev
Requires-Dist: flake8 ; extra == 'dev'
Requires-Dist: pre-commit ; extra == 'dev'
Provides-Extra: doc
Requires-Dist: numpydoc ; extra == 'doc'
Requires-Dist: sphinx-bootstrap-theme ; extra == 'doc'
Requires-Dist: sphinx-gallery ; extra == 'doc'
Provides-Extra: test
Requires-Dist: pytest ; extra == 'test'
Requires-Dist: pytest-cov ; extra == 'test'
Requires-Dist: pytest-env ; extra == 'test'
